inafish/__init__.py
inafish-1.0.1.dist-info/licenses/LICENSE
inafish-1.0.1.dist-info/METADATA
inafish-1.0.1.dist-info/WHEEL
inafish-1.0.1.dist-info/top_level.txt
inafish-1.0.1.dist-info/RECORD
