Metadata-Version: 2.4
Name: inafish
Version: 1.0.1
Summary: A simple library for inafishent (but smol) compression. >[_]
Author-email: The Odd Cell <me@oddcell.ca>
Project-URL: Homepage, https://github.com/theoddcell/inafish
Classifier: Programming Language :: Python :: 3
Classifier: License :: Public Domain
Classifier: Operating System :: OS Independent
License-File: LICENSE
Dynamic: license-file
